cpssdk/__init__.py
cpssdk/cpsfeatures.py
cpssdk/cpsfilter.py
cpssdk/cpsos.py
cpssdk/cpspandas-test.py
cpssdk/cpspandas.py
cpssdk/cpsplot-test.py
cpssdk/cpsplot.py
cpssdk/cpsraster.py
cpssdk/cpsspatio-test.py
cpssdk/cpsspatio.py
cpssdk/cpsspatio_interval.py
cpssdk/cpstime.py
cpssdk-0.0.2.dist-info/DESCRIPTION.rst
cpssdk-0.0.2.dist-info/METADATA
cpssdk-0.0.2.dist-info/RECORD
cpssdk-0.0.2.dist-info/WHEEL
cpssdk-0.0.2.dist-info/metadata.json
cpssdk-0.0.2.dist-info/top_level.txt
