Metadata-Version: 2.0
Name: cpssdk
Version: 0.0.2
Summary: cps time processing package
Home-page: http://zhihanfang.com
Author: ogre
Author-email: ezhihan@gmail.com
License: MIT Licence
Keywords: pip,datacanvas,eds,xiaoh
Platform: any
Requires-Dist: datetime
Requires-Dist: numpy
Requires-Dist: pandas
Requires-Dist: simplejson
